BSD_LICENSE.txt
BSD_NOTICE.txt
MANIFEST.in
README.md
post-install-setup.sh
requirements.txt
setup.py
config/README.md
config/liota.conf
config/logging.json
examples/README.md
examples/dell5k_edge_system_graphite.py
examples/dell5k_edge_system_iotcc_websocket.py
examples/dell5k_edge_system_with_filter_iotcc.py
examples/dk300_edge_system_iotcc_graphite.py
examples/multi_metric_simulated_edge_system_graphite.py
examples/sampleProp.conf
examples/simulated_edge_system_graphite.py
examples/simulated_graphite_event_based.py
examples/simulated_graphite_temp.py
examples/model_simulated/README.md
examples/model_simulated/graphite_bike_simulated.py
examples/model_simulated/graphite_thermistor_simulated.py
examples/model_simulated/iotcc_bike_simulated.py
examples/model_simulated/iotcc_thermistor_simulated.py
examples/mqtt/README.md
examples/mqtt/dcc_comms/README.md
examples/mqtt/dcc_comms/aws_iot/sampleProp.conf
examples/mqtt/dcc_comms/aws_iot/simulated_home_auto_gen_topic.py
examples/mqtt/dcc_comms/aws_iot/simulated_home_topic_per_metric.py
examples/mqtt/dcc_comms/iotcc/dell5k_edge_system_iotcc_mqtt.py
examples/mqtt/dcc_comms/iotcc/sampleProp.conf
examples/mqtt/device_comms/README.md
examples/mqtt/device_comms/iotcc/iotcc_simulated_mqtt.py
examples/mqtt/device_comms/iotcc/samplePropMqtt.conf
liota/__init__.py
liota.egg-info/PKG-INFO
liota.egg-info/SOURCES.txt
liota.egg-info/dependency_links.txt
liota.egg-info/requires.txt
liota.egg-info/top_level.txt
liota/actions/__init__.py
liota/alerts/__init__.py
liota/core/__init__.py
liota/core/device_discovery.py
liota/core/discovery_simulator.py
liota/core/metric_handler.py
liota/core/package_manager.py
liota/dcc_comms/__init__.py
liota/dcc_comms/dcc_comms.py
liota/dcc_comms/mqtt_dcc_comms.py
liota/dcc_comms/socket_comms.py
liota/dcc_comms/websocket_dcc_comms.py
liota/dccs/__init__.py
liota/dccs/aws_iot.py
liota/dccs/dcc.py
liota/dccs/graphite.py
liota/dccs/iotcc.py
liota/dev_sims/__init__.py
liota/dev_sims/coap.py
liota/dev_sims/device_simulator.py
liota/dev_sims/mqtt.py
liota/dev_sims/named_pipe.py
liota/dev_sims/socket_clnt.py
liota/device_comms/__init__.py
