Metadata-Version: 1.1
Name: liota
Version: 0.4.1
Summary: Little IoT Agent (liota)
Home-page: https://github.com/vmware/liota
Author: Kohli Vaibhav (VMware)
Author-email: vkohli@vmware.com
License: BSD
Keywords: iot liota agent
Platform: Linux
Classifier: Development Status :: 3 - Alpha
Classifier: Intended Audience :: Developers
Classifier: Topic :: Software Development :: Libraries :: Python Modules
Classifier: Operating System :: POSIX :: Linux
Classifier: License :: OSI Approved :: BSD License
Classifier: Programming Language :: Python :: 2.7
